Metadata-Version: 2.1
Name: Wafacul
Version: 0.1
Summary: Simple library in python for test
Author: Wafa alhammadi
